inferflow/__init__.py
inferflow/py.typed
inferflow/types.py
inferflow/_C/__init__.pyi
inferflow/_C/ops/__init__.pyi
inferflow/_C/ops/bbox.pyi
inferflow/_utils/__init__.py
inferflow/_utils/image.py
inferflow/_utils/yolo/__init__.py
inferflow/_utils/yolo/np.py
inferflow/_utils/yolo/torch.py
inferflow/asyncio/__init__.py
inferflow/asyncio/batch/__init__.py
inferflow/asyncio/batch/dynamic.py
inferflow/asyncio/pipeline/__init__.py
inferflow/asyncio/pipeline/classification/__init__.py
inferflow/asyncio/pipeline/classification/onnx.py
inferflow/asyncio/pipeline/classification/torch.py
inferflow/asyncio/pipeline/detection/__init__.py
inferflow/asyncio/pipeline/detection/onnx.py
inferflow/asyncio/pipeline/detection/torch.py
inferflow/asyncio/pipeline/segmentation/__init__.py
inferflow/asyncio/pipeline/segmentation/onnx.py
inferflow/asyncio/pipeline/segmentation/torch.py
inferflow/asyncio/runtime/__init__.py
inferflow/asyncio/runtime/onnx.py
inferflow/asyncio/runtime/tensorrt.py
inferflow/asyncio/runtime/torch.py
inferflow/asyncio/workflow/__init__.py
inferflow/asyncio/workflow/decorators.py
inferflow/asyncio/workflow/tasks.py
inferflow/batch/__init__.py
inferflow/batch/dynamic.py
inferflow/pipeline/__init__.py
inferflow/pipeline/classification/__init__.py
inferflow/pipeline/classification/onnx.py
inferflow/pipeline/classification/torch.py
inferflow/pipeline/detection/__init__.py
inferflow/pipeline/detection/onnx.py
inferflow/pipeline/detection/torch.py
inferflow/pipeline/segmentation/__init__.py
inferflow/pipeline/segmentation/onnx.py
inferflow/pipeline/segmentation/torch.py
inferflow/runtime/__init__.py
inferflow/runtime/onnx.py
inferflow/runtime/tensorrt.py
inferflow/runtime/torch.py
inferflow/workflow/__init__.py
inferflow/workflow/decorators.py
inferflow/workflow/tasks.py
inferflow-0.1.1a3.dist-info/licenses/LICENSE
inferflow-0.1.1a3.dist-info/METADATA
inferflow-0.1.1a3.dist-info/WHEEL
inferflow-0.1.1a3.dist-info/top_level.txt
inferflow-0.1.1a3.dist-info/RECORD
