Metadata-Version: 2.4
Name: inferflow
Version: 0.1.1a3
Summary: Universal Inference Pipeline Framework for Computer Vision
Author-email: BoChenSHEN <6goddddddd@gmail.com>
License: MIT
Project-URL: Documentation, https://6ixgodd.github.io/inferflow
Project-URL: Homepage, https://github.com/6ixGODD/inferflow
Project-URL: Issues, https://github.com/6ixGODD/inferflow/issues
Project-URL: Repository, https://github.com/6ixGODD/inferflow
Keywords: computer-vision,deep-learning,inference,pipeline
Classifier: Development Status :: 3 - Alpha
Classifier: Intended Audience :: Developers
Classifier: Intended Audience :: Science/Research
Classifier: License :: OSI Approved :: MIT License
Classifier: Programming Language :: Python :: 3 :: Only
Classifier: Programming Language :: Python :: 3.10
Classifier: Programming Language :: Python :: 3.11
Classifier: Programming Language :: Python :: 3.12
Classifier: Programming Language :: Python :: 3.13
Classifier: Programming Language :: Python :: 3.14
Classifier: Topic :: Scientific/Engineering :: Artificial Intelligence
Classifier: Topic :: Software Development :: Libraries :: Python Modules
Requires-Python: <3.15,>=3.10
License-File: LICENSE
Requires-Dist: numpy<2.3,>=2
Requires-Dist: opencv-python<4.12,>=4.10
Requires-Dist: pillow<13,>=10
Provides-Extra: dev
Requires-Dist: build>=1; extra == "dev"
Requires-Dist: halo<0.0.32,>=0.0.30; extra == "dev"
Requires-Dist: inferflow[docs,lint,test,torch]; extra == "dev"
Requires-Dist: pip-tools>=7; extra == "dev"
Requires-Dist: pre-commit<4,>=3; extra == "dev"
Requires-Dist: pyyaml<7,>=6; extra == "dev"
Provides-Extra: docs
Requires-Dist: mkdocs<2,>=1.5; extra == "docs"
Requires-Dist: mkdocs-material<10,>=9.5; extra == "docs"
Requires-Dist: mkdocs-minify-plugin<1,>=0.8; extra == "docs"
Requires-Dist: mkdocstrings[python]<1,>=0.24; extra == "docs"
Requires-Dist: pymdown-extensions<11,>=10; extra == "docs"
Provides-Extra: lint
Requires-Dist: mypy<2,>=1.8; extra == "lint"
Requires-Dist: pylint<4,>=3; extra == "lint"
Requires-Dist: ruff<1,>=0.1; extra == "lint"
Provides-Extra: onnx
Requires-Dist: onnxruntime<2,>=1.14; extra == "onnx"
Provides-Extra: onnx-gpu
Requires-Dist: onnxruntime-gpu<2,>=1.14; extra == "onnx-gpu"
Provides-Extra: tensorrt
Requires-Dist: pycuda<2026,>=2022.1; extra == "tensorrt"
Requires-Dist: tensorrt<11,>=8.5; extra == "tensorrt"
Provides-Extra: test
Requires-Dist: mypy<2,>=1.8; extra == "test"
Requires-Dist: pytest<10,>=8; extra == "test"
Requires-Dist: pytest-asyncio<1,>=0.23; extra == "test"
Requires-Dist: pytest-cov<6,>=4; extra == "test"
Provides-Extra: torch
Requires-Dist: torch<3,>=2.1; extra == "torch"
Requires-Dist: torchvision<1,>=0.15; extra == "torch"
Dynamic: license-file
